8-Bit Register/register.v
`timescale 1ns/100ps
`default_nettype none

module register_8bit (
    output reg [7:0] Q,
    input wire [7:0] D,
    input wire clk,
    input wire en,
    input wire rst
);
    always @(posedge clk or posedge rst) begin
        if (rst)
            Q <= 8'b0;
        else if (en)
            Q <= D;
    end
endmodule // register_8bit

module register_file (
    output wire [7:0] r_data1,
    output wire [7:0] r_data2,
    input wire clk,
    input wire we,
    input wire rst,
    input wire [2:0] w_addr,
    input wire [2:0] r_addr1,
    input wire [2:0] r_addr2,
    input wire [7:0] w_data
);
    wire [7:0] reg_out [0:7]; // 2D array of wires
    wire [7:0] we_bus;

    genvar i;
    generate
        for (i = 0; i < 8; i = i + 1) begin : regs
            assign we_bus[i] = we && (w_addr == i);
            register_8bit reg_inst (
                .Q(reg_out[i]),
                .D(w_data),
                .clk(clk),
                .en(we_bus[i]),
                .rst(rst)
            );
        end
    endgenerate

    assign r_data1 = reg_out[r_addr1];
    assign r_data2 = reg_out[r_addr2];

endmodule // register_file

8-Bit Register/tb_register.v
`timescale 1ns/100ps
`default_nettype none

module tb_register_file;
    parameter CLK_PERIOD = 10;

    reg clk, rst, we;
    reg [2:0] w_addr, r_addr1, r_addr2;
    reg [7:0] w_data;
    wire [7:0] r_data1, r_data2;

    register_file uut (
        .r_data1(r_data1),
        .r_data2(r_data2),
        .clk(clk),
        .we(we),
        .rst(rst),
        .w_addr(w_addr),
        .r_addr1(r_addr1),
        .r_addr2(r_addr2),
        .w_data(w_data)
    );

    // generate clock signal
    initial begin
        clk = 0;
        forever #(CLK_PERIOD / 2) clk = ~clk;
    end

    // Test sequence
    initial begin
        rst = 1;
        we = 0;
        w_addr = 0;
        w_data = 0;
        r_addr1 = 0;
        r_addr2 = 0;

        #(CLK_PERIOD * 1.5) rst = 0;

        // Testing reset
        $display("[%0t]: reset test", $time);
        verify_read(0, 0, 0, 0);
        verify_read(7, 0, 0, 0);

        // Testing read/write
        $display("\n[%0t]: read/write test", $time);
        write_reg(1, 8'hA5);
        #1;
        verify_read(1, 0, 8'hA5, 8'h00);

        // Testing concurrent read ports
        $display("\n[%0t]: concurrent read ports test", $time);
        write_reg(2, 8'h3C);
        write_reg(3, 8'hF0);
        #1;
        verify_read(2, 3, 8'h3C, 8'hF0);

        // Testing write suppression (we=0)
        $display("\n[%0t]: write suppression test", $time);
        we = 0;
        w_addr = 1;
        w_data = 8'hFF;
        @(posedge clk);
        #1;
        verify_read(1, 0, 8'hA5, 0);

        // Testing address decoding
        $display("\n[%0t]: address decoding test", $time);
        test_all_addresses();

        // Testing timings
        $display("\n[%0t]: timing tests", $time);
        timing_tests();

        $display("\n[%0t] All tests completed", $time);
        $finish;
    end

    task write_reg;
        input [2:0] addr;
        input [7:0] data;
        begin
            we = 1;
            w_addr = addr;
            w_data = data;
            @(posedge clk);
            we = 0;
            $display("[%0t] Wrote 0x%h to register %0d", $time, data, addr);
        end
    endtask

    task verify_read;
		input [2:0] addr1;
		input [2:0] addr2;
		input [7:0] expected1;
		input [7:0] expected2;
		begin
			r_addr1 = addr1;
			r_addr2 = addr2;
			#1;
			if (r_data1 !== expected1 || r_data2 !== expected2) begin
				$error("[%0t] ERROR: r_addr1=%0d (got 0x%h, expected 0x%h) | r_addr2=%0d (got 0x%h, expected 0x%h)",
						$time, addr1, r_data1, expected1, addr2, r_data2, expected2);
			end else begin
				$display("[%0t] PASS: r_addr1=%0d=0x%h, r_addr2=%0d=0x%h",
						$time, addr1, r_data1, addr2, r_data2);
			end
		end
	endtask

    task test_all_addresses;
        integer i;
        begin
            for (i = 0; i < 8; i = i + 1) begin
                write_reg(i, 8'h10 + i);
                #1;
                verify_read(i, 0, 8'h10 + i, 8'h00);
            end
        end
    endtask

    task timing_tests;
        begin
            w_data = 8'hAA;
            w_addr = 0;
            we = 1;
            #(CLK_PERIOD - 2); // Too close to clock edge
            @(posedge clk);
            #1;
            verify_read(0, 0, 8'h10, 0); // Should not change

            // Correct timing rate
            #(CLK_PERIOD / 4);
            w_data = 8'hBB;
            @(posedge clk);
            #1;
            verify_read(0, 0, 8'hBB, 0);
        end
    endtask

    initial begin
        $dumpfile("sim_register.vcd");
        $dumpvars(0, tb_register_file);
    end
endmodule

8-Bit Register/sim_register.vcd
$date
	Sun Apr 06 16:41:49 2025
$end
$version
	Icarus Verilog
$end
$timescale
	100ps
$end
$scope module tb_register_file $end
$var wire 8 ! r_data1 [7:0] $end
$var wire 8 " r_data2 [7:0] $end
$var reg 1 # clk $end
$var reg 3 $ r_addr1 [2:0] $end
$var reg 3 % r_addr2 [2:0] $end
$var reg 1 & rst $end
$var reg 3 ' w_addr [2:0] $end
$var reg 8 ( w_data [7:0] $end
$var reg 1 ) we $end
$scope module uut $end
$var wire 1 * clk $end
$var wire 3 + r_addr1 [2:0] $end
$var wire 3 , r_addr2 [2:0] $end
$var wire 8 - r_data1 [7:0] $end
$var wire 8 . r_data2 [7:0] $end
$var wire 1 / rst $end
$var wire 3 0 w_addr [2:0] $end
$var wire 8 1 w_data [7:0] $end
$var wire 1 2 we $end
$var wire 8 3 we_bus [7:0] $end
$scope begin regs[0] $end
$scope module reg_inst $end
$var wire 8 4 D [7:0] $end
$var wire 1 * clk $end
$var wire 1 5 en $end
$var wire 1 / rst $end
$var reg 8 6 Q [7:0] $end
$upscope $end
$upscope $end
$scope begin regs[1] $end
$scope module reg_inst $end
$var wire 8 7 D [7:0] $end
$var wire 1 * clk $end
$var wire 1 8 en $end
$var wire 1 / rst $end
$var reg 8 9 Q [7:0] $end
$upscope $end
$upscope $end
$scope begin regs[2] $end
$scope module reg_inst $end
$var wire 8 : D [7:0] $end
$var wire 1 * clk $end
$var wire 1 ; en $end
$var wire 1 / rst $end
$var reg 8 < Q [7:0] $end
$upscope $end
$upscope $end
$scope begin regs[3] $end
$scope module reg_inst $end
$var wire 8 = D [7:0] $end
$var wire 1 * clk $end
$var wire 1 > en $end
$var wire 1 / rst $end
$var reg 8 ? Q [7:0] $end
$upscope $end
$upscope $end
$scope begin regs[4] $end
$scope module reg_inst $end
$var wire 8 @ D [7:0] $end
$var wire 1 * clk $end
$var wire 1 A en $end
$var wire 1 / rst $end
$var reg 8 B Q [7:0] $end
$upscope $end
$upscope $end
$scope begin regs[5] $end
$scope module reg_inst $end
$var wire 8 C D [7:0] $end
$var wire 1 * clk $end
$var wire 1 D en $end
$var wire 1 / rst $end
$var reg 8 E Q [7:0] $end
$upscope $end
$upscope $end
$scope begin regs[6] $end
$scope module reg_inst $end
$var wire 8 F D [7:0] $end
$var wire 1 * clk $end
$var wire 1 G en $end
$var wire 1 / rst $end
$var reg 8 H Q [7:0] $end
$upscope $end
$upscope $end
$scope begin regs[7] $end
$scope module reg_inst $end
$var wire 8 I D [7:0] $end
$var wire 1 * clk $end
$var wire 1 J en $end
$var wire 1 / rst $end
$var reg 8 K Q [7:0] $end
$upscope $end
$upscope $end
$upscope $end
$scope task test_all_addresses $end
$var integer 32 L i [31:0] $end
$upscope $end
$scope task timing_tests $end
$upscope $end
$scope task verify_read $end
$var reg 3 M addr1 [2:0] $end
$var reg 3 N addr2 [2:0] $end
$var reg 8 O expected1 [7:0] $end
$var reg 8 P expected2 [7:0] $end
$upscope $end
$scope task write_reg $end
$var reg 3 Q addr [2:0] $end
$var reg 8 R data [7:0] $end
$upscope $end
$upscope $end
$enddefinitions $end
#0
$dumpvars
bx R
bx Q
bx P
bx O
bx N
bx M
bx L
b0 K
0J
b0 I
b0 H
0G
b0 F
b0 E
0D
b0 C
b0 B
0A
b0 @
b0 ?
0>
b0 =
b0 <
0;
b0 :
b0 9
08
b0 7
b0 6
05
b0 4
b0 3
02
b0 1
b0 0
1/
b0 .
b0 -
b0 ,
b0 +
0*
0)
b0 (
b0 '
1&
b0 %
b0 $
0#
b0 "
b0 !
$end
#50
1#
1*
#100
0#
0*
#150
1#
1*
b0 P
b0 O
b0 N
b0 M
0&
0/
#160
b111 $
b111 +
b111 M
#170
18
b10 3
b10100101 (
b10100101 1
b10100101 4
b10100101 7
b10100101 :
b10100101 =
b10100101 @
b10100101 C
b10100101 F
b10100101 I
b1 '
b1 0
1)
12
b10100101 R
b1 Q
#200
0#
0*
#250
b10100101 9
08
b0 3
0)
02
1#
1*
#260
b1 $
b1 +
b10100101 !
b10100101 -
b10100101 O
b1 M
#270
1;
b100 3
b111100 (
b111100 1
b111100 4
b111100 7
b111100 :
b111100 =
b111100 @
b111100 C
b111100 F
b111100 I
b10 '
b10 0
1)
12
b111100 R
b10 Q
#300
0#
0*
#350
b11110000 <
0;
1>
b1000 3
b11110000 (
b11110000 1
b11110000 4
b11110000 7
b11110000 :
b11110000 =
b11110000 @
b11110000 C
b11110000 F
b11110000 I
b11 '
b11 0
b11110000 R
b11 Q
1)
12
1#
1*
#400
0#
0*
#450
b11110000 ?
0>
b0 3
0)
02
1#
1*
#460
b11 %
b11 ,
b11110000 "
b11110000 .
b10 $
b10 +
b11110000 !
b11110000 -
b11110000 P
b111100 O
b11 N
b10 M
#470
b11111111 (
b11111111 1
b11111111 4
b11111111 7
b11111111 :
b11111111 =
b11111111 @
b11111111 C
b11111111 F
b11111111 I
b1 '
b1 0
#500
0#
0*
#550
1#
1*
#560
b0 %
b0 ,
b0 "
b0 .
b1 $
b1 +
b10100101 !
b10100101 -
b0 P
b10100101 O
b0 N
b1 M
#570
15
b1 3
b10000 (
b10000 1
b10000 4
b10000 7
b10000 :
b10000 =
b10000 @
b10000 C
b10000 F
b10000 I
b0 '
b0 0
1)
12
b10000 R
b0 Q
b0 L
#600
0#
0*
#650
b10000 6
b10000 "
b10000 .
05
b0 3
0)
02
1#
1*
#660
b0 $
b0 +
b10000 !
b10000 -
b10000 O
b0 M
#670
18
b10 3
b10001 (
b10001 1
b10001 4
b10001 7
b10001 :
b10001 =
b10001 @
b10001 C
b10001 F
b10001 I
b1 '
b1 0
1)
12
b10001 R
b1 Q
b1 L
#700
0#
0*
#750
b10001 9
08
b0 3
0)
02
1#
1*
#760
b1 $
b1 +
b10001 !
b10001 -
b10001 O
b1 M
#770
1;
b100 3
b10010 (
b10010 1
b10010 4
b10010 7
b10010 :
b10010 =
b10010 @
b10010 C
b10010 F
b10010 I
b10 '
b10 0
1)
12
b10010 R
b10 Q
b10 L
#800
0#
0*
#850
b10010 <
0;
b0 3
0)
02
1#
1*
#860
b10 $
b10 +
b10010 !
b10010 -
b10010 O
b10 M
#870
1>
b1000 3
b10011 (
b10011 1
b10011 4
b10011 7
b10011 :
b10011 =
b10011 @
b10011 C
b10011 F
b10011 I
b11 '
b11 0
1)
12
b10011 R
b11 Q
b11 L
#900
0#
0*
#950
b10011 ?
0>
b0 3
0)
02
1#
1*
#960
b11 $
b11 +
b10011 !
b10011 -
b10011 O
b11 M
#970
1A
b10000 3
b10100 (
b10100 1
b10100 4
b10100 7
b10100 :
b10100 =
b10100 @
b10100 C
b10100 F
b10100 I
b100 '
b100 0
1)
12
b10100 R
b100 Q
b100 L
#1000
0#
0*
#1050
b10100 B
0A
b0 3
0)
02
1#
1*
#1060
b100 $
b100 +
b10100 !
b10100 -
b10100 O
b100 M
#1070
1D
b100000 3
b10101 (
b10101 1
b10101 4
b10101 7
b10101 :
b10101 =
b10101 @
b10101 C
b10101 F
b10101 I
b101 '
b101 0
1)
12
b10101 R
b101 Q
b101 L
#1100
0#
0*
#1150
b10101 E
0D
b0 3
0)
02
1#
1*
#1160
b101 $
b101 +
b10101 !
b10101 -
b10101 O
b101 M
#1170
1G
b1000000 3
b10110 (
b10110 1
b10110 4
b10110 7
b10110 :
b10110 =
b10110 @
b10110 C
b10110 F
b10110 I
b110 '
b110 0
1)
12
b10110 R
b110 Q
b110 L
#1200
0#
0*
#1250
b10110 H
0G
b0 3
0)
02
1#
1*
#1260
b110 $
b110 +
b10110 !
b10110 -
b10110 O
b110 M
#1270
1J
b10000000 3
b10111 (
b10111 1
b10111 4
b10111 7
b10111 :
b10111 =
b10111 @
b10111 C
b10111 F
b10111 I
b111 '
b111 0
1)
12
b10111 R
b111 Q
b111 L
#1300
0#
0*
#1350
b10111 K
0J
b0 3
0)
02
1#
1*
#1360
b111 $
b111 +
b10111 !
b10111 -
b10111 O
b111 M
#1370
15
b1 3
1)
12
b0 '
b0 0
b10101010 (
b10101010 1
b10101010 4
b10101010 7
b10101010 :
b10101010 =
b10101010 @
b10101010 C
b10101010 F
b10101010 I
b1000 L
#1400
0#
0*
#1450
b10101010 6
b10101010 "
b10101010 .
1#
1*
#1460
b0 $
b0 +
b10101010 !
b10101010 -
b10000 O
b0 M
#1490
b10111011 (
b10111011 1
b10111011 4
b10111011 7
b10111011 :
b10111011 =
b10111011 @
b10111011 C
b10111011 F
b10111011 I
#1500
0#
0*
#1550
b10111011 6
b10111011 !
b10111011 -
b10111011 "
b10111011 .
1#
1*
#1560
b10111011 O
